ntu_course_planner/__init__.py
ntu_course_planner/config.py
ntu_course_planner/course.py
ntu_course_planner/main.py
ntu_course_planner/planner.py
ntu_course_planner/ssl_type.py
ntu_course_planner-1.0.3.dist-info/LICENSE
ntu_course_planner-1.0.3.dist-info/METADATA
ntu_course_planner-1.0.3.dist-info/WHEEL
ntu_course_planner-1.0.3.dist-info/entry_points.txt
ntu_course_planner-1.0.3.dist-info/top_level.txt
ntu_course_planner-1.0.3.dist-info/RECORD
