Metadata-Version: 2.1
Name: ntu-course-planner
Version: 1.0.3
Summary: A course planner for Nanyang Technological University students
Home-page: https://github.com/koallen/ntu-course-planner-cli
Author: Liu Siyuan
Author-email: weifengzi2009@gmail.com
License: MIT
Keywords: course,planner,Nanyang Technological University
Platform: UNKNOWN
Classifier: Development Status :: 5 - Production/Stable
Classifier: Environment :: Console
Classifier: Intended Audience :: End Users/Desktop
Classifier: Intended Audience :: Developers
Classifier: License :: OSI Approved :: MIT License
Classifier: Natural Language :: English
Classifier: Programming Language :: Python :: 3 :: Only
Classifier: Topic :: Utilities
Requires-Dist: requests
Requires-Dist: beautifulsoup4
